liquer/__init__.py
liquer/app.py
liquer/blueprint.py
liquer/cache.py
liquer/commands.py
liquer/config.py
liquer/constants.py
liquer/context.py
liquer/dependencies.py
liquer/indexer.py
liquer/metadata.py
liquer/parser.py
liquer/pool.py
liquer/query.py
liquer/recipes.py
liquer/remote_store.py
liquer/s3_store.py
liquer/state.py
liquer/state_types.py
liquer/store.py
liquer/template.py
liquer/tools.py
liquer/tui.py
liquer/util.py
liquer/web.py
liquer/ext/__init__.py
liquer/ext/basic.py
liquer/ext/dataframe_batches.py
liquer/ext/lq_datafusion.py
liquer/ext/lq_hxl.py
liquer/ext/lq_keras.py
liquer/ext/lq_matplotlib.py
liquer/ext/lq_openpyxl.py
liquer/ext/lq_pandas.py
liquer/ext/lq_pil.py
liquer/ext/lq_plotly.py
liquer/ext/lq_polars.py
liquer/ext/lq_pptx.py
liquer/ext/lq_pygments.py
liquer/ext/lq_python.py
liquer/ext/lq_qdrant.html
liquer/ext/lq_qdrant.py
liquer/ext/lq_sklearn_regression.py
liquer/ext/lq_sweetviz.py
liquer/ext/lq_whoosh.html
liquer/ext/lq_whoosh.py
liquer/ext/meta.py
liquer/ext/rag.py
liquer/server/__init__.py
liquer/server/blueprint.py
liquer/server/fastapi.py
liquer/server/handlers.py
liquer/server/tornado_handlers.py
liquer/server/static/index.html
liquer/server/static/liquer.js
liquer_framework-0.9.9.dist-info/LICENSE
liquer_framework-0.9.9.dist-info/METADATA
liquer_framework-0.9.9.dist-info/WHEEL
liquer_framework-0.9.9.dist-info/top_level.txt
liquer_framework-0.9.9.dist-info/RECORD
