Metadata-Version: 2.1
Name: liquer-framework
Version: 0.9.9
Summary: LiQuer - Query in (URL) link
Home-page: https://github.com/orest-d/liquer
Author: Orest Dubay
Author-email: orest3.dubay@gmail.com
Classifier: Programming Language :: Python :: 3
Classifier: License :: OSI Approved :: MIT License
Classifier: Operating System :: OS Independent
License-File: LICENSE
Requires-Dist: Flask
